example_package/__init__.py
example_package/example.py
hello_world_antonylion-1.0.3.dist-info/LICENSE
hello_world_antonylion-1.0.3.dist-info/METADATA
hello_world_antonylion-1.0.3.dist-info/WHEEL
hello_world_antonylion-1.0.3.dist-info/top_level.txt
hello_world_antonylion-1.0.3.dist-info/RECORD
