Metadata-Version: 2.1
Name: hello-world-antonylion
Version: 1.0.3
Summary: My first Python package
Author-email: John Doe <john@example.com>
Requires-Python: >=3.8
License-File: LICENSE
Requires-Dist: numpy
Requires-Dist: pandas
